{"link":"2331493","name":"PremiumSoft Navicat For MySQL Enterprise Edition 8.2.15","date":"20-Окт-09 18:56","author":"sxd","description":"\nPremiumSoft Naviсat For MySQL Enterprise Edition 8.2.15Год выпуска: 2009\nВерсия: 8.2.15\nРазработчик: PremiumSoft ™ CyberTech Ltd\nПлатформа: x86\nСовместимость с Vista: полнаяСистемные требования:\n● OS: Microsoft Windows 2000, XP, Vista, Server 2003, Server 2008, Windows 7\n● CPU: Pentium II processor or above\n● RAM: 64 megabytes (MB)\n● HDD: Hard-disk space vary depending on installation. Full installation requires 10 MB of available hard-disk spaceЯзык интерфейса: Только английский\nТаблэтка: ПрисутствуетОписание: NaviCat For MySQL 8.2.15 – это утилита обеспечивает мощный графический интерфейс для для работы с базами данных MySQL. Легкий и интуитивно понятный интерфейс делает Navicat незаменимым инструментом для работы. Кроме обычных функций для администрирования баз данных, Navicat также предлагает функции импорта/экспорта, создания резервных копий и пересылки данных с помощью удобных помощников, позволяет конвертировать Acess to MySQL, MS SQL to MySQL, Excel to MySQL и синхронизировать.\n\nОсновные функции:\n- HTTP Tunnel\n- SSH Tunnel\n- Синхронизация данных и струкктуры\n- SQL консоль\n- поддержка всех версий MySQL\n- поддержка множественных соединений для локальных и удалённых MySQL серверов\n- создание и удаление баз данных, таблиц, индексов и пользователей\n- поддержка Unicode\n- импорт/экспорт данных в 5 наиболее популярных форматов: XLS, CSV, TXT, DBF and XML\n- создание и запуск SQL queries\n- возможность выполнения основных задач по расписанию\n- поддержка переноса данных с одного MySQL сервера на другой\n- бэкап и восстановление баз данных\n- управление правами доступа [Security Configuration]\nи др.\n\n\n\nСкриншоты\n\n\n\n\n\n\n  \n Набор в группу «Хранители» - Помогите сохранить редкие раздачи  ","magnet_link":"magnet:?xt=urn:btih:9ED1534207BEC2AB299980A66172248627853D28&tr=http%3A%2F%2Fbt4.t-ru.org%2Fann%3Fmagnet&dn=PremiumSoft%20Navicat%20For%20MySQL%20Enterprise%20Edition%208.2.15","torrent_link":"dl.php?t=2331493","thanked_list":[{"id":"48812263","name":"v0ff4ik19 ","data":"(01-Май-23)"},{"id":"49162790","name":"zcxads ","data":"(26-Сен-22)"},{"id":"45059301","name":"vrady ","data":"(26-Апр-22)"},{"id":"47996078","name":"zzcy ","data":"(29-Мар-22)"},{"id":"30313126","name":"netwar22 ","data":"(31-Янв-22)"},{"id":"42104588","name":"breakcore78 ","data":"(30-Янв-22)"},{"id":"23434120","name":"Bazelik000111 ","data":"(08-Окт-21)"},{"id":"44069492","name":"AlexBrauni ","data":"(12-Май-21)"},{"id":"27266052","name":"munfox ","data":"(03-Апр-21)"},{"id":"6762744","name":"cr34t0r ","data":"(08-Фев-21)"},{"id":"16909125","name":"Maksimenko_86 ","data":"(13-Янв-21)"},{"id":"21394534","name":"Ильдар-Asha ","data":"(24-Дек-20)"},{"id":"17334406","name":"straighteyes ","data":"(20-Сен-20)"},{"id":"39358034","name":"Liomsa ","data":"(11-Сен-20)"},{"id":"17995035","name":"zavyala ","data":"(08-Сен-20)"},{"id":"19739161","name":"Adrianus_West ","data":"(24-Июн-20)"},{"id":"40614501","name":"rubin20-21 ","data":"(13-Дек-19)"},{"id":"28322959","name":"Первой ","data":"(18-Июн-18)"},{"id":"15949892","name":"cherniy73 ","data":"(18-Янв-18)"},{"id":"37067477","name":"Kolya Goyshick ","data":"(08-Дек-17)"},{"id":"33105372","name":"Gvilyam ","data":"(04-Май-17)"},{"id":"18517456","name":"dnk73dnk ","data":"(11-Июл-16)"},{"id":"19228246","name":"ramzay_77 ","data":"(07-Июн-16)"},{"id":"40382408","name":"cybercyborg ","data":"(06-Май-16)"},{"id":"16999663","name":"rufil ","data":"(15-Апр-16)"},{"id":"28379508","name":"lobster666 ","data":"(14-Дек-15)"},{"id":"10963732","name":"serg060606 ","data":"(03-Ноя-15)"},{"id":"13541974","name":"goocool ","data":"(26-Сен-15)"},{"id":"0","name":"Гость","data":"(14-Авг-15)"},{"id":"22639202","name":"indrikis2 ","data":"(20-Апр-15)"},{"id":"2671689","name":"Vladi545 ","data":"(12-Мар-15)"},{"id":"11350701","name":"DarkHost_DH ","data":"(28-Дек-14)"},{"id":"0","name":"Гость","data":"(15-Окт-14)"},{"id":"25777853","name":"leonkorosten ","data":"(14-Сен-14)"},{"id":"0","name":"Гость","data":"(10-Июл-14)"},{"id":"28055230","name":"alastrion ","data":"(06-Июн-14)"},{"id":"22913474","name":"Dik_Voker ","data":"(23-Апр-14)"},{"id":"33193728","name":"Cherepah1 ","data":"(24-Янв-14)"},{"id":"24535920","name":"ITSS-KZ ","data":"(12-Янв-14)"},{"id":"17115408","name":"Ashanar ","data":"(09-Янв-14)"},{"id":"16116590","name":"vladn82 ","data":"(07-Янв-14)"},{"id":"23183486","name":"denpodz ","data":"(03-Дек-13)"},{"id":"24050438","name":"ravshan1987 ","data":"(18-Ноя-13)"},{"id":"19195998","name":"Sitrapom ","data":"(12-Ноя-13)"},{"id":"18530058","name":"dreamtec ","data":"(25-Окт-13)"},{"id":"20877627","name":"Nosenko-777 ","data":"(11-Сен-13)"},{"id":"14722045","name":"mcpnt ","data":"(12-Май-13)"},{"id":"0","name":"Гость","data":"(03-Фев-13)"},{"id":"0","name":"Гость","data":"(02-Окт-12)"},{"id":"0","name":"Гость","data":"(07-Июн-11)"},{"id":"0","name":"Гость","data":"(12-Фев-11)"},{"id":"0","name":"Гость","data":"(06-Янв-10)"},{"id":"0","name":"Гость","data":"(25-Ноя-09)"},{"id":"0","name":"Гость","data":"(19-Ноя-09)"}]}