{"link":"5584659","name":"PowerBuilder .NET / PowerBuilder Classic 12.6.0.4098 x86 [2016, ENG]","date":"08-Июл-18 11:41","author":"мегавольт","description":"\nPowerBuilder .NET / PowerBuilder Classic 12.6Год/Дата Выпуска: 2016\nВерсия: 12.6 Build 4098\nРазработчик: Sybase / SAPРазрядность: 32bit\nЯзык интерфейса: Английский\nТаблэтка: присутствует\nСистемные требования:\n• Операционная система Microsoft Windows XP SP3 или новее;\n• процессор Pentium 4 или новее;\n• минимум 512 МБ ОЗУ;\n• 700 МБ пространства жесткого диска;\n• Microsoft .NET Framework 4.0 или новее.\nОписание: PowerBuilder — интегрированная среда разработки приложений баз данных с собственным скриптовым языком PowerScript.\nДоп. информация: Компания Sybase представила новую версию своего инструментария для ускоренной разработки приложений Sybase PowerBuilder 12. Пакет Sybase PowerBuilder обеспечивает быстрый переход с платформы Win32 на платформу Microsoft .NET, а также предлагает полную поддержку технологии построения графических интерфейсов WPF (Windows Presentation Foundation).Новая архитектура пакета Sybase PowerBuilder 12 активно использует инфраструктуру среды разработки Microsoft Visual Studio для обеспечения максимальной продуктивности при создании приложений PowerBuilder на базе технологии .NET Framework. Как и прежде для доступа к бизнес-логике пакет PowerBuilder 12 требует всего пять строк кода там, где на других языках необходимо писать целые сотни строк. Подобную эффективность обеспечивает запатентованная фирменная технология DataWindow. Благодаря адаптации технологии DataWindow под язык C# среда PowerBuilder 12 теперь позволяет создавать контролируемый код с поддержкой технологии Microsoft WPF, повышая продуктивность, гибкость и защищенность разработки. Кроме того, это единственный в своем роде продукт, который позволяет эффективно использовать уже готовый код для Win32 и переходить на технологию .NET Framework с минимальными затратами.\n\nСкриншоты\n\n \n\n\n\nСкриншоты окна About\n\n \n \n\n  \n Набор в группу «Хранители» - Помогите сохранить редкие раздачи  ","magnet_link":"magnet:?xt=urn:btih:9F570C8561D733342BE5DAAF7F42307054490116&tr=http%3A%2F%2Fbt4.t-ru.org%2Fann%3Fmagnet&dn=PowerBuilder%20.NET%20%2F%20PowerBuilder%20Classic%2012.6.0.4098%20x86%20%5B2016%2C%20ENG%5D","torrent_link":"dl.php?t=5584659","thanked_list":[{"id":"3091619","name":"e730 ","data":"(05-Мар-23)"},{"id":"7390723","name":"kikos1978 ","data":"(02-Мар-23)"},{"id":"2263869","name":"Overfiend ","data":"(13-Сен-22)"},{"id":"9656659","name":"petru108 ","data":"(22-Май-22)"},{"id":"465453","name":"odpt ","data":"(02-Дек-21)"},{"id":"45165806","name":"rovanchek ","data":"(04-Окт-21)"},{"id":"10792044","name":"vvac ","data":"(25-Авг-21)"},{"id":"14796248","name":"Аленький1 ","data":"(24-Авг-21)"},{"id":"13781210","name":"ASButov ","data":"(24-Мар-21)"},{"id":"39277945","name":"ajost ","data":"(18-Май-20)"},{"id":"8919350","name":"zaplavsky ","data":"(02-Мар-20)"},{"id":"16908628","name":"arkadus10 ","data":"(12-Ноя-19)"},{"id":"26915176","name":"xtfr2215h ","data":"(17-Сен-19)"},{"id":"26889335","name":"ig-petrov ","data":"(24-Авг-19)"},{"id":"23705251","name":"rtiksde ","data":"(28-Июн-19)"},{"id":"5889741","name":"tvv2110 ","data":"(18-Июн-19)"},{"id":"26655781","name":"movntq ","data":"(09-Май-19)"},{"id":"18016472","name":"partizanin1 ","data":"(01-Фев-19)"},{"id":"27466161","name":"hjuma ","data":"(06-Янв-19)"},{"id":"16138497","name":"sovex74 ","data":"(18-Дек-18)"},{"id":"5374778","name":"SHnuR666 ","data":"(15-Авг-18)"},{"id":"37965634","name":"DormidontLoewe ","data":"(06-Авг-18)"},{"id":"19209427","name":"NickWolf ","data":"(03-Авг-18)"},{"id":"12757613","name":"Igor_zg ","data":"(09-Июл-18)"},{"id":"15760837","name":"IGHG ","data":"(08-Июл-18)"},{"id":"4760475","name":"grdraf ","data":"(08-Июл-18)"},{"id":"2576503","name":"pegas76 ","data":"(08-Июл-18)"}]}